registries/__init__.py
registries/_version.py
registries/errors.py
registries/items.py
registries/py.typed
registries/registry.py
registries/tests/__init__.py
registries/tests/test_entry_point_registry.py
registries/tests/test_ordered_registry.py
registries/tests/test_registry.py
registries-1.0.dist-info/LICENSE
registries-1.0.dist-info/METADATA
registries-1.0.dist-info/WHEEL
registries-1.0.dist-info/top_level.txt
registries-1.0.dist-info/RECORD
